docs/__init__.py
webb_scraping/__init__.py
webb_scraping/calculations.py
webb_scraping/target.py
webb_scraping-0.3.0.dist-info/METADATA
webb_scraping-0.3.0.dist-info/WHEEL
webb_scraping-0.3.0.dist-info/top_level.txt
webb_scraping-0.3.0.dist-info/RECORD
