Metadata-Version: 2.1
Name: webb-scraping
Version: 0.3.0
Summary: Web scraping for JWST
Home-page: https://webb-scraping.readthedocs.io
Author: Arjun Baliga Savel
Author-email: asavel@gmail.com
Maintainer: Arjun Baliga Savel
Maintainer-email: asavel@gmail.com
License: MIT
Platform: UNKNOWN
Classifier: Development Status :: 4 - Beta
Classifier: Intended Audience :: Developers
Classifier: Intended Audience :: Science/Research
Classifier: Natural Language :: English
Classifier: License :: OSI Approved :: MIT License
Classifier: Operating System :: Unix
Classifier: Operating System :: MacOS
Classifier: Programming Language :: Python
Classifier: Programming Language :: Python :: 3.6
Classifier: Programming Language :: Python :: 3.7
Classifier: Programming Language :: Python :: 3.8
Classifier: Topic :: Scientific/Engineering :: Astronomy
Requires-Dist: tqdm
Requires-Dist: astropy
Requires-Dist: pygments (>=2.4.1)
Requires-Dist: nbsphinx (==0.5.1)
Requires-Dist: nbconvert (<6,>=5.5.0)
Requires-Dist: numpy
Requires-Dist: astroquery
Requires-Dist: bs4
Requires-Dist: requests
